{
"success":true,
"receipt": "base64encodedstring",
"transaction" : {
    "reversalType" : 0,
    "referenceNum" : "170510114446",
    "responseCode" : "116",
    "emvAppName" : "",
    "merchantFee" : 0,
    "txnType" : "txn.credit.sale",
    "entryType" : 1,
    "amountDue" : 0,
    "authCode" : "",
    "transactionResult" : 0,
    "orderNumber" : "",
    "emvAppLabel" : "",
    "emvAid" : "",
    "dateTime" : "5\/10\/17, 11:44:46 AM Mountain Standard Time",
    "avsText" : "",
    "cardType" : 1,
    "groupType" : "grp.credit",
    "signaturePresent" : 0,
    "token" : "9780750511465556",
    "approvedAmt" : 0,
    "last4Digits" : "5556",
    "tipAmount" : 0,
    "batchNum" : 1,
    "purchaseCard" : 0,
    "responseText" : "DECLINED-051",
    "txnNum" : 40,
    "totalAmount" : 1,
    "cvvResult" : 0,
    "cvvText" : "",
    "avsResult" : "",
    "baseAmount" : 1,
    "cardName" : "VISA"
  },
  "credentials" : {
    "mcc" : "7922",
    "datawireId" : "xxx",
    "visaBid" : "xxx",
    "merchantId" : "RCTST0000009046",
    "nashvilleId" : "1175451",
    "terminalId" : "00000002",
    "visaAuar" : "xxx",
    "groupId" : "10001"
  },
  "signature" : "base64encodedstring"
}


SUCCESS:  VISA DEBIT AS DEBIT
  "transaction" : {
    "reversalType" : 0,
    "referenceNum" : "170510114535",
    "responseCode" : "000",
    "emvAppName" : "",
    "merchantFee" : 0,
    "txnType" : "txn.debit.sale",
    "entryType" : 1,
    "amountDue" : 0,
    "authCode" : "211901",
    "transactionResult" : 0,
    "orderNumber" : "1494441918919",
    "emvAppLabel" : "",
    "emvAid" : "",
    "dateTime" : "5\/10\/17, 11:45:35 AM Mountain Standard Time",
    "avsText" : "",
    "cardType" : 0,
    "groupType" : "grp.debit",
    "signaturePresent" : 0,
    "token" : "9780750511465556",
    "approvedAmt" : 1,
    "last4Digits" : "5556",
    "tipAmount" : 0,
    "batchNum" : 1,
    "purchaseCard" : 0,
    "responseText" : "",
    "txnNum" : 40,
    "totalAmount" : 1,
    "cvvResult" : 0,
    "cvvText" : "",
    "avsResult" : "",
    "baseAmount" : 1,
    "cardName" : "Debit"
  },
  "credentials" : {
    "mcc" : "7922",
    "datawireId" : "xxx",
    "visaBid" : "xxx",
    "merchantId" : "RCTST0000009046",
    "nashvilleId" : "1175451",
    "terminalId" : "00000002",
    "visaAuar" : "xxx",
    "groupId" : "10001"
  }